horsql/__init__.py
horsql/common.py
horsql/database.py
horsql/operators.py
horsql/query_builder.py
horsql-0.1.22.dist-info/METADATA
horsql-0.1.22.dist-info/WHEEL
horsql-0.1.22.dist-info/RECORD
